{
  "project_info": {
    "project_number": "589456157906",
    "firebase_url": "https://fir-fa33d-default-rtdb.firebaseio.com",
    "project_id": "fir-fa33d",
    "storage_bucket": "fir-fa33d.appspot.com"
  },
  "client": [
    {
      "client_info": {
        "mobilesdk_app_id": "1:589456157906:android:7d02fb0a2cf401641e110b",
        "android_client_info": {
          "package_name": "com.example.demo"
        }
      },
      "oauth_client": [
        {
          "client_id": "589456157906-ec4k252oviaf9nqv7edo1gq8cl29kart.apps.googleusercontent.com",
          "client_type": 3
        }
      ],
      "api_key": [
        {
          "current_key": "AIzaSyC0oKhxCtXtLnlk0abIXLkkTmuhE8ImMVA"
        }
      ],
      "services": {
        "appinvite_service": {
          "other_platform_oauth_client": [
            {
              "client_id": "589456157906-ec4k252oviaf9nqv7edo1gq8cl29kart.apps.googleusercontent.com",
              "client_type": 3
            }
          ]
        }
      }
    }
  ],
  "configuration_version": "1"
}